[
  {
    "name":     "简书",
    "url":      "http://www.jianshu.com/trending/now",
    "icon":     "http://static.jianshu.io/assets/icon114-fcef1133c955e46bf55e2a60368f687b.png",
    "selector": "h4>a"
  },
  {
    "icon":     "http://daily.zhihu.com/favicon.ico",
    "url":      "http://daily.zhihu.com/",
    "selector": ".box>a",
    "name":     "知乎日报"
  },
  {"icon":"https://static.zhihu.com/static/revved/img/ios/touch-icon-152.f361b474.png","url":"http://www.zhihu.com/explore/recommendations","name":"知乎编辑推荐","selector":"a.question_link"}
]
